Workbook

Sheet Questions
A2: Business Case : | B2: The company wants to analyze sales performance across different product categories to identify best-selling products, revenue distribution,and market trends.
B3: The different sheets contains different data, using these information available in the sheets complete the questions below
A5: SI.No | B5: Questions | C5: Marks
A6: 1 | B6: In the Product_Sales and Product_pricing, certain columns (highlighted in yellow) are missing data. Update these columns using the data available in the other sheets. | C6: 5
A7: 2 | B7: In the Product_Sales table, create a column named "Sales Contribution (%)" (column highlighted in red font) and calculate the percentage of each product's sales out of the total sales. Hint: Sales Contribution (%) = (Sales of the product / Total sales) * 100 | C7: 5
A8: 3 | B8: Display the Total Sales and Average Order Value per Product Category. Sort the data in descending order based on Total Sales. Hint: AOV = Total Sales/Total Orders where Total Orders = Number of unique transaction id's. (Provide your solution in the sheet labeled "Q3"). | C8: 6
A9: 4 | B9: Identify the most purchased product based on the total quantity sold. If multiple products have the highest quantity, list all of them. (Provide your solution in the sheet labeled "Q4"). | C9: 6
A10: 5 | B10: Create a Pivot Table to compare the total sales for each product category, and generate an appropriate Pivot Chart to visualize the data - Ensure the chart has a proper title and is aligned correctly. (Provide your solution in the sheet labeled "Q5"). | C10: 8

Sheet Product_Sales
A1: prod_id | B1: qty | C1: discount | D1: member | E1: txn_id | F1: start_txn_time | G1: Price | H1: Total Sales Amount | I1: sales contribution% | J1: category | K1: order count
A2: c4a632 | B2: 4 | C2: 17 | D2: t | E2: 54f307 | F2: 0.04147338 | G2: =_xlfn.XLOOKUP($A2,Product_pricing!$B:$B,Product_pricing!$C:$C) -> 13 | H2: =B2*G2*(1-C2/100) -> 43.16 | I2: =(H2/SUM($H:$H))*1000 -> 0.038086032 | J2: =_xlfn.XLOOKUP(A2,Product_Details!$A:$A,Product_Details!$G:$G,"mens") -> Womens | K2: =COUNTIFS($J:$J, J2) / COUNTIFS($J:$J, J2, $E:$E, E2) -> 7535
A3: 5d267b | B3: 4 | C3: 17 | D3: t | E3: 54f307 | F3: 0.04147338 | G3: =_xlfn.XLOOKUP($A3,Product_pricing!$B:$B,Product_pricing!$C:$C) -> 40 | H3: =B3*G3*(1-C3/100) -> 132.8 | I3: =(H3/SUM($H:$H))*1000 -> 0.11718779 | J3: =_xlfn.XLOOKUP(A3,Product_Details!$A:$A,Product_Details!$G:$G,"mens") -> Mens | K3: =COUNTIFS($J:$J, J3) / COUNTIFS($J:$J, J3, $E:$E, E3) -> 2520
A4: b9a74d | B4: 4 | C4: 17 | D4: t | E4: 54f307 | F4: 0.04147338 | G4: =_xlfn.XLOOKUP($A4,Product_pricing!$B:$B,Product_pricing!$C:$C) -> 17 | H4: =B4*G4*(1-C4/100) -> 56.44 | I4: =(H4/SUM($H:$H))*1000 -> 0.049804811 | J4: =_xlfn.XLOOKUP(A4,Product_Details!$A:$A,Product_Details!$G:$G,"mens") -> Mens | K4: =COUNTIFS($J:$J, J4) / COUNTIFS($J:$J, J4, $E:$E, E4) -> 2520
A5: 2feb6b | B5: 2 | C5: 17 | D5: t | E5: 54f307 | F5: 0.04147338 | G5: =_xlfn.XLOOKUP($A5,Product_pricing!$B:$B,Product_pricing!$C:$C) -> 29 | H5: =B5*G5*(1-C5/100) -> 48.14 | I5: =(H5/SUM($H:$H))*1000 -> 0.042480574 | J5: =_xlfn.XLOOKUP(A5,Product_Details!$A:$A,Product_Details!$G:$G,"mens") -> Mens | K5: =COUNTIFS($J:$J, J5) / COUNTIFS($J:$J, J5, $E:$E, E5) -> 2520
A6: c4a632 | B6: 5 | C6: 21 | D6: t | E6: 26cc98 | F6: 0.027086806 | G6: =_xlfn.XLOOKUP($A6,Product_pricing!$B:$B,Product_pricing!$C:$C) -> 13 | H6: =B6*G6*(1-C6/100) -> 51.35 | I6: =(H6/SUM($H:$H))*1000 -> 0.045313201 | J6: =_xlfn.XLOOKUP(A6,Product_Details!$A:$A,Product_Details!$G:$G,"mens") -> Womens | K6: =COUNTIFS($J:$J, J6) / COUNTIFS($J:$J, J6, $E:$E, E6) -> 2511.6667
A7: e31d39 | B7: 2 | C7: 21 | D7: t | E7: 26cc98 | F7: 0.027086806 | G7: =_xlfn.XLOOKUP($A7,Product_pricing!$B:$B,Product_pricing!$C:$C) -> 10 | H7: =B7*G7*(1-C7/100) -> 15.8 | I7: =(H7/SUM($H:$H))*1000 -> 0.013942523 | J7: =_xlfn.XLOOKUP(A7,Product_Details!$A:$A,Product_Details!$G:$G,"mens") -> Womens | K7: =COUNTIFS($J:$J, J7) / COUNTIFS($J:$J, J7, $E:$E, E7) -> 2511.6667
A8: 72f5d4 | B8: 3 | C8: 21 | D8: t | E8: 26cc98 | F8: 0.027086806 | G8: =_xlfn.XLOOKUP($A8,Product_pricing!$B:$B,Product_pricing!$C:$C) -> 19 | H8: =B8*G8*(1-C8/100) -> 45.03 | I8: =(H8/SUM($H:$H))*1000 -> 0.039736191 | J8: =_xlfn.XLOOKUP(A8,Product_Details!$A:$A,Product_Details!$G:$G,"mens") -> Womens | K8: =COUNTIFS($J:$J, J8) / COUNTIFS($J:$J, J8, $E:$E, E8) -> 2511.6667
A9: 2a2353 | B9: 3 | C9: 21 | D9: t | E9: 26cc98 | F9: 0.027086806 | G9: =_xlfn.XLOOKUP($A9,Product_pricing!$B:$B,Product_pricing!$C:$C) -> 57 | H9: =B9*G9*(1-C9/100) -> 135.09 | I9: =(H9/SUM($H:$H))*1000 -> 0.11920857 | J9: =_xlfn.XLOOKUP(A9,Product_Details!$A:$A,Product_Details!$G:$G,"mens") -> Mens | K9: =COUNTIFS($J:$J, J9) / COUNTIFS($J:$J, J9, $E:$E, E9) -> 3780
A10: f084eb | B10: 3 | C10: 21 | D10: t | E10: 26cc98 | F10: 0.027086806 | G10: =_xlfn.XLOOKUP($A10,Product_pricing!$B:$B,Product_pricing!$C:$C) -> 36 | H10: =B10*G10*(1-C10/100) -> 85.32 | I10: =(H10/SUM($H:$H))*1000 -> 0.075289625 | J10: =_xlfn.XLOOKUP(A10,Product_Details!$A:$A,Product_Details!$G:$G,"mens") -> Mens | K10: =COUNTIFS($J:$J, J10) / COUNTIFS($J:$J, J10, $E:$E, E10) -> 3780
A11: c4a632 | B11: 1 | C11: 21 | D11: f | E11: ef648d | F11: 0.012699074 | G11: =_xlfn.XLOOKUP($A11,Product_pricing!$B:$B,Product_pricing!$C:$C) -> 13 | H11: =B11*G11*(1-C11/100) -> 10.27 | I11: =(H11/SUM($H:$H))*1000 -> 0.0090626401 | J11: =_xlfn.XLOOKUP(A11,Product_Details!$A:$A,Product_Details!$G:$G,"mens") -> Womens | K11: =COUNTIFS($J:$J, J11) / COUNTIFS($J:$J, J11, $E:$E, E11) -> 1883.75
A12: e83aa3 | B12: 5 | C12: 21 | D12: f | E12: ef648d | F12: 0.012699074 | G12: =_xlfn.XLOOKUP($A12,Product_pricing!$B:$B,Product_pricing!$C:$C) -> 32 | H12: =B12*G12*(1-C12/100) -> 126.4 | I12: =(H12/SUM($H:$H))*1000 -> 0.11154019 | J12: =_xlfn.XLOOKUP(A12,Product_Details!$A:$A,Product_Details!$G:$G,"mens") -> Womens | K12: =COUNTIFS($J:$J, J12) / COUNTIFS($J:$J, J12, $E:$E, E12) -> 1883.75
A13: d5e9a6 | B13: 1 | C13: 21 | D13: f | E13: ef648d | F13: 0.012699074 | G13: =_xlfn.XLOOKUP($A13,Product_pricing!$B:$B,Product_pricing!$C:$C) -> 23 | H13: =B13*G13*(1-C13/100) -> 18.17 | I13: =(H13/SUM($H:$H))*1000 -> 0.016033902 | J13: =_xlfn.XLOOKUP(A13,Product_Details!$A:$A,Product_Details!$G:$G,"mens") -> Womens | K13: =COUNTIFS($J:$J, J13) / COUNTIFS($J:$J, J13, $E:$E, E13) -> 1883.75
... A89: b9a74d | B89: 4 | C89: 13 | D89: t | E89: 500bf9 | F89: 0.028649306 | G89: =_xlfn.XLOOKUP($A89,Product_pricing!$B:$B,Product_pricing!$C:$C) -> 17 | H89: =B89*G89*(1-C89/100) -> 59.16 | I89: =(H89/SUM($H:$H))*1000 -> 0.052205043 | J89: =_xlfn.XLOOKUP(A89,Product_Details!$A:$A,Product_Details!$G:$G,"mens") -> Mens | K89: =COUNTIFS($J:$J, J89) / COUNTIFS($J:$J, J89, $E:$E, E89) -> 7560
A90: e83aa3 | B90: 4 | C90: 24 | D90: t | E90: 34601 | F90: 0.024737269 | G90: =_xlfn.XLOOKUP($A90,Product_pricing!$B:$B,Product_pricing!$C:$C) -> 32 | H90: =B90*G90*(1-C90/100) -> 97.28 | I90: =(H90/SUM($H:$H))*1000 -> 0.085843586 | J90: =_xlfn.XLOOKUP(A90,Product_Details!$A:$A,Product_Details!$G:$G,"mens") -> Womens | K90: =COUNTIFS($J:$J, J90) / COUNTIFS($J:$J, J90, $E:$E, E90) -> 2511.6667
A91: e31d39 | B91: 4 | C91: 24 | D91: t | E91: 34601 | F91: 0.024737269 | G91: =_xlfn.XLOOKUP($A91,Product_pricing!$B:$B,Product_pricing!$C:$C) -> 10 | H91: =B91*G91*(1-C91/100) -> 30.4 | I91: =(H91/SUM($H:$H))*1000 -> 0.026826121 | J91: =_xlfn.XLOOKUP(A91,Product_Details!$A:$A,Product_Details!$G:$G,"mens") -> Womens | K91: =COUNTIFS($J:$J, J91) / COUNTIFS($J:$J, J91, $E:$E, E91) -> 2511.6667
A92: 9ec847 | B92: 5 | C92: 24 | D92: t | E92: 34601 | F92: 0.024737269 | G92: =_xlfn.XLOOKUP($A92,Product_pricing!$B:$B,Product_pricing!$C:$C) -> 54 | H92: =B92*G92*(1-C92/100) -> 205.2 | I92: =(H92/SUM($H:$H))*1000 -> 0.18107631 | J92: =_xlfn.XLOOKUP(A92,Product_Details!$A:$A,Product_Details!$G:$G,"mens") -> Womens | K92: =COUNTIFS($J:$J, J92) / COUNTIFS($J:$J, J92, $E:$E, E92) -> 2511.6667
A93: f084eb | B93: 3 | C93: 24 | D93: t | E93: 34601 | F93: 0.024737269 | G93: =_xlfn.XLOOKUP($A93,Product_pricing!$B:$B,Product_pricing!$C:$C) -> 36 | H93: =B93*G93*(1-C93/100) -> 82.08 | I93: =(H93/SUM($H:$H))*1000 -> 0.072430526 | J93: =_xlfn.XLOOKUP(A93,Product_Details!$A:$A,Product_Details!$G:$G,"mens") -> Mens | K93: =COUNTIFS($J:$J, J93) / COUNTIFS($J:$J, J93, $E:$E, E93) -> 3780
A94: b9a74d | B94: 3 | C94: 24 | D94: t | E94: 34601 | F94: 0.024737269 | G94: =_xlfn.XLOOKUP($A94,Product_pricing!$B:$B,Product_pricing!$C:$C) -> 17 | H94: =B94*G94*(1-C94/100) -> 38.76 | I94: =(H94/SUM($H:$H))*1000 -> 0.034203304 | J94: =_xlfn.XLOOKUP(A94,Product_Details!$A:$A,Product_Details!$G:$G,"mens") -> Mens | K94: =COUNTIFS($J:$J, J94) / COUNTIFS($J:$J, J94, $E:$E, E94) -> 3780
A95: e83aa3 | B95: 4 | C95: 1 | D95: t | E95: a88a5e | F95: 0.039042824 | G95: =_xlfn.XLOOKUP($A95,Product_pricing!$B:$B,Product_pricing!$C:$C) -> 32 | H95: =B95*G95*(1-C95/100) -> 126.72 | I95: =(H95/SUM($H:$H))*1000 -> 0.11182257 | J95: =_xlfn.XLOOKUP(A95,Product_Details!$A:$A,Product_Details!$G:$G,"mens") -> Womens | K95: =COUNTIFS($J:$J, J95) / COUNTIFS($J:$J, J95, $E:$E, E95) -> 7535
A96: 5d267b | B96: 4 | C96: 1 | D96: t | E96: a88a5e | F96: 0.039042824 | G96: =_xlfn.XLOOKUP($A96,Product_pricing!$B:$B,Product_pricing!$C:$C) -> 40 | H96: =B96*G96*(1-C96/100) -> 158.4 | I96: =(H96/SUM($H:$H))*1000 -> 0.13977821 | J96: =_xlfn.XLOOKUP(A96,Product_Details!$A:$A,Product_Details!$G:$G,"mens") -> Mens | K96: =COUNTIFS($J:$J, J96) / COUNTIFS($J:$J, J96, $E:$E, E96) -> 7560
A97: d5e9a6 | B97: 3 | C97: 19 | D97: f | E97: 9a9653 | F97: 0.0089131944 | G97: =_xlfn.XLOOKUP($A97,Product_pricing!$B:$B,Product_pricing!$C:$C) -> 23 | H97: =B97*G97*(1-C97/100) -> 55.89 | I97: =(H97/SUM($H:$H))*1000 -> 0.04931947 | J97: =_xlfn.XLOOKUP(A97,Product_Details!$A:$A,Product_Details!$G:$G,"mens") -> Womens | K97: =COUNTIFS($J:$J, J97) / COUNTIFS($J:$J, J97, $E:$E, E97) -> 7535
A98: c8d436 | B98: 1 | C98: 19 | D98: f | E98: 9a9653 | F98: 0.0089131944 | G98: =_xlfn.XLOOKUP($A98,Product_pricing!$B:$B,Product_pricing!$C:$C) -> 10 | H98: =B98*G98*(1-C98/100) -> 8.1 | I98: =(H98/SUM($H:$H))*1000 -> 0.0071477493 | J98: =_xlfn.XLOOKUP(A98,Product_Details!$A:$A,Product_Details!$G:$G,"mens") -> Mens | K98: =COUNTIFS($J:$J, J98) / COUNTIFS($J:$J, J98, $E:$E, E98) -> 1890
A99: f084eb | B99: 2 | C99: 19 | D99: f | E99: 9a9653 | F99: 0.0089131944 | G99: =_xlfn.XLOOKUP($A99,Product_pricing!$B:$B,Product_pricing!$C:$C) -> 36 | H99: =B99*G99*(1-C99/100) -> 58.32 | I99: =(H99/SUM($H:$H))*1000 -> 0.051463795 | J99: =_xlfn.XLOOKUP(A99,Product_Details!$A:$A,Product_Details!$G:$G,"mens") -> Mens | K99: =COUNTIFS($J:$J, J99) / COUNTIFS($J:$J, J99, $E:$E, E99) -> 1890
A100: b9a74d | B100: 2 | C100: 19 | D100: f | E100: 9a9653 | F100: 0.0089131944 | G100: =_xlfn.XLOOKUP($A100,Product_pricing!$B:$B,Product_pricing!$C:$C) -> 17 | H100: =B100*G100*(1-C100/100) -> 27.54 | I100: =(H100/SUM($H:$H))*1000 -> 0.024302347 | J100: =_xlfn.XLOOKUP(A100,Product_Details!$A:$A,Product_Details!$G:$G,"mens") -> Mens | K100: =COUNTIFS($J:$J, J100) / COUNTIFS($J:$J, J100, $E:$E, E100) -> 1890
A101: 2feb6b | B101: 2 | C101: 19 | D101: f | E101: 9a9653 | F101: 0.0089131944 | G101: =_xlfn.XLOOKUP($A101,Product_pricing!$B:$B,Product_pricing!$C:$C) -> 29 | H101: =B101*G101*(1-C101/100) -> 46.98 | I101: =(H101/SUM($H:$H))*1000 -> 0.041456946 | J101: =_xlfn.XLOOKUP(A101,Product_Details!$A:$A,Product_Details!$G:$G,"mens") -> Mens | K101: =COUNTIFS($J:$J, J101) / COUNTIFS($J:$J, J101, $E:$E, E101) -> 1890
A102: c4a632 | B102: 5 | C102: 14 | D102: f | E102: 1edc69 | F102: 0.022729167 | G102: =_xlfn.XLOOKUP($A102,Product_pricing!$B:$B,Product_pricing!$C:$C) -> 13 | H102: =B102*G102*(1-C102/100) -> 55.9 | I102: =(H102/SUM($H:$H))*1000 -> 0.049328294 | J102: =_xlfn.XLOOKUP(A102,Product_Details!$A:$A,Product_Details!$G:$G,"mens") -> Womens | K102: =COUNTIFS($J:$J, J102) / COUNTIFS($J:$J, J102, $E:$E, E102) -> 1883.75
A103: e83aa3 | B103: 5 | C103: 14 | D103: f | E103: 1edc69 | F103: 0.022729167 | G103: =_xlfn.XLOOKUP($A103,Product_pricing!$B:$B,Product_pricing!$C:$C) -> 32 | H103: =B103*G103*(1-C103/100) -> 137.6 | I103: =(H103/SUM($H:$H))*1000 -> 0.12142349 | J103: =_xlfn.XLOOKUP(A103,Product_Details!$A:$A,Product_Details!$G:$G,"mens") -> Womens | K103: =COUNTIFS($J:$J, J103) / COUNTIFS($J:$J, J103, $E:$E, E103) -> 1883.75
A104: 72f5d4 | B104: 3 | C104: 14 | D104: f | E104: 1edc69 | F104: 0.022729167 | G104: =_xlfn.XLOOKUP($A104,Product_pricing!$B:$B,Product_pricing!$C:$C) -> 19 | H104: =B104*G104*(1-C104/100) -> 49.02 | I104: =(H104/SUM($H:$H))*1000 -> 0.04325712 | J104: =_xlfn.XLOOKUP(A104,Product_Details!$A:$A,Product_Details!$G:$G,"mens") -> Womens | K104: =COUNTIFS($J:$J, J104) / COUNTIFS($J:$J, J104, $E:$E, E104) -> 1883.75
A105: 9ec847 | B105: 5 | C105: 14 | D105: f | E105: 1edc69 | F105: 0.022729167 | G105: =_xlfn.XLOOKUP($A105,Product_pricing!$B:$B,Product_pricing!$C:$C) -> 54 | H105: =B105*G105*(1-C105/100) -> 232.2 | I105: =(H105/SUM($H:$H))*1000 -> 0.20490215 | J105: =_xlfn.XLOOKUP(A105,Product_Details!$A:$A,Product_Details!$G:$G,"mens") -> Womens | K105: =COUNTIFS($J:$J, J105) / COUNTIFS($J:$J, J105, $E:$E, E105) -> 1883.75
A106: c8d436 | B106: 3 | C106: 14 | D106: f | E106: 1edc69 | F106: 0.022729167 | G106: =_xlfn.XLOOKUP($A106,Product_pricing!$B:$B,Product_pricing!$C:$C) -> 10 | H106: =B106*G106*(1-C106/100) -> 25.8 | I106: =(H106/SUM($H:$H))*1000 -> 0.022766905 | J106: =_xlfn.XLOOKUP(A106,Product_Details!$A:$A,Product_Details!$G:$G,"mens") -> Mens | K106: =COUNTIFS($J:$J, J106) / COUNTIFS($J:$J, J106, $E:$E, E106) -> 3780
... A142: 2feb6b | B142: 5 | C142: 12 | D142: t | E142: 2cf0ed | F142: 0.041508102 | G142: =_xlfn.XLOOKUP($A142,Product_pricing!$B:$B,Product_pricing!$C:$C) -> 29 | H142: =B142*G142*(1-C142/100) -> 127.6 | I142: =(H142/SUM($H:$H))*1000 -> 0.11259911 | J142: =_xlfn.XLOOKUP(A142,Product_Details!$A:$A,Product_Details!$G:$G,"mens") -> Mens | K142: =COUNTIFS($J:$J, J142) / COUNTIFS($J:$J, J142, $E:$E, E142) -> 2520
A143: e31d39 | B143: 5 | C143: 16 | D143: t | E143: 9e+37 | F143: 0.017722222 | G143: =_xlfn.XLOOKUP($A143,Product_pricing!$B:$B,Product_pricing!$C:$C) -> 10 | H143: =B143*G143*(1-C143/100) -> 42 | I143: =(H143/SUM($H:$H))*1000 -> 0.037062404 | J143: =_xlfn.XLOOKUP(A143,Product_Details!$A:$A,Product_Details!$G:$G,"mens") -> Womens | K143: =COUNTIFS($J:$J, J143) / COUNTIFS($J:$J, J143, $E:$E, E143) -> 2511.6667
A144: d5e9a6 | B144: 1 | C144: 16 | D144: t | E144: 9e+37 | F144: 0.017722222 | G144: =_xlfn.XLOOKUP($A144,Product_pricing!$B:$B,Product_pricing!$C:$C) -> 23 | H144: =B144*G144*(1-C144/100) -> 19.32 | I144: =(H144/SUM($H:$H))*1000 -> 0.017048706 | J144: =_xlfn.XLOOKUP(A144,Product_Details!$A:$A,Product_Details!$G:$G,"mens") -> Womens | K144: =COUNTIFS($J:$J, J144) / COUNTIFS($J:$J, J144, $E:$E, E144) -> 2511.6667
A145: 72f5d4 | B145: 1 | C145: 16 | D145: t | E145: 9e+37 | F145: 0.017722222 | G145: =_xlfn.XLOOKUP($A145,Product_pricing!$B:$B,Product_pricing!$C:$C) -> 19 | H145: =B145*G145*(1-C145/100) -> 15.96 | I145: =(H145/SUM($H:$H))*1000 -> 0.014083713 | J145: =_xlfn.XLOOKUP(A145,Product_Details!$A:$A,Product_Details!$G:$G,"mens") -> Womens | K145: =COUNTIFS($J:$J, J145) / COUNTIFS($J:$J, J145, $E:$E, E145) -> 2511.6667
A146: f084eb | B146: 3 | C146: 16 | D146: t | E146: 9e+37 | F146: 0.017722222 | G146: =_xlfn.XLOOKUP($A146,Product_pricing!$B:$B,Product_pricing!$C:$C) -> 36 | H146: =B146*G146*(1-C146/100) -> 90.72 | I146: =(H146/SUM($H:$H))*1000 -> 0.080054792 | J146: =_xlfn.XLOOKUP(A146,Product_Details!$A:$A,Product_Details!$G:$G,"mens") -> Mens | K146: =COUNTIFS($J:$J, J146) / COUNTIFS($J:$J, J146, $E:$E, E146) -> 7560
A147: d5e9a6 | B147: 5 | C147: 7 | D147: t | E147: d1a249 | F147: 0.015505787 | G147: =_xlfn.XLOOKUP($A147,Product_pricing!$B:$B,Product_pricing!$C:$C) -> 23 | H147: =B147*G147*(1-C147/100) -> 106.95 | I147: =(H147/SUM($H:$H))*1000 -> 0.094376763 | J147: =_xlfn.XLOOKUP(A147,Product_Details!$A:$A,Product_Details!$G:$G,"mens") -> Womens | K147: =COUNTIFS($J:$J, J147) / COUNTIFS($J:$J, J147, $E:$E, E147) -> 2511.6667
A148: 72f5d4 | B148: 4 | C148: 7 | D148: t | E148: d1a249 | F148: 0.015505787 | G148: =_xlfn.XLOOKUP($A148,Product_pricing!$B:$B,Product_pricing!$C:$C) -> 19 | H148: =B148*G148*(1-C148/100) -> 70.68 | I148: =(H148/SUM($H:$H))*1000 -> 0.062370731 | J148: =_xlfn.XLOOKUP(A148,Product_Details!$A:$A,Product_Details!$G:$G,"mens") -> Womens | K148: =COUNTIFS($J:$J, J148) / COUNTIFS($J:$J, J148, $E:$E, E148) -> 2511.6667
A149: 9ec847 | B149: 5 | C149: 7 | D149: t | E149: d1a249 | F149: 0.015505787 | G149: =_xlfn.XLOOKUP($A149,Product_pricing!$B:$B,Product_pricing!$C:$C) -> 54 | H149: =B149*G149*(1-C149/100) -> 251.1 | I149: =(H149/SUM($H:$H))*1000 -> 0.22158023 | J149: =_xlfn.XLOOKUP(A149,Product_Details!$A:$A,Product_Details!$G:$G,"mens") -> Womens | K149: =COUNTIFS($J:$J, J149) / COUNTIFS($J:$J, J149, $E:$E, E149) -> 2511.6667
A150: 2a2353 | B150: 3 | C150: 7 | D150: t | E150: d1a249 | F150: 0.015505787 | G150: =_xlfn.XLOOKUP($A150,Product_pricing!$B:$B,Product_pricing!$C:$C) -> 57 | H150: =B150*G150*(1-C150/100) -> 159.03 | I150: =(H150/SUM($H:$H))*1000 -> 0.14033414 | J150: =_xlfn.XLOOKUP(A150,Product_Details!$A:$A,Product_Details!$G:$G,"mens") -> Mens | K150: =COUNTIFS($J:$J, J150) / COUNTIFS($J:$J, J150, $E:$E, E150) -> 3780
A151: 2feb6b | B151: 3 | C151: 7 | D151: t | E151: d1a249 | F151: 0.015505787 | G151: =_xlfn.XLOOKUP($A151,Product_pricing!$B:$B,Product_pricing!$C:$C) -> 29 | H151: =B151*G151*(1-C151/100) -> 80.91 | I151: =(H151/SUM($H:$H))*1000 -> 0.071398073 | J151: =_xlfn.XLOOKUP(A151,Product_Details!$A:$A,Product_Details!$G:$G,"mens") -> Mens | K151: =COUNTIFS($J:$J, J151) / COUNTIFS($J:$J, J151, $E:$E, E151) -> 3780
A152: c4a632 | B152: 2 | C152: 22 | D152: t | E152: f77cc2 | F152: 0.020461806 | G152: =_xlfn.XLOOKUP($A152,Product_pricing!$B:$B,Product_pricing!$C:$C) -> 13 | H152: =B152*G152*(1-C152/100) -> 20.28 | I152: =(H152/SUM($H:$H))*1000 -> 0.017895846 | J152: =_xlfn.XLOOKUP(A152,Product_Details!$A:$A,Product_Details!$G:$G,"mens") -> Womens | K152: =COUNTIFS($J:$J, J152) / COUNTIFS($J:$J, J152, $E:$E, E152) -> 1883.75
A153: e83aa3 | B153: 5 | C153: 22 | D153: t | E153: f77cc2 | F153: 0.020461806 | G153: =_xlfn.XLOOKUP($A153,Product_pricing!$B:$B,Product_pricing!$C:$C) -> 32 | H153: =B153*G153*(1-C153/100) -> 124.8 | I153: =(H153/SUM($H:$H))*1000 -> 0.11012828 | J153: =_xlfn.XLOOKUP(A153,Product_Details!$A:$A,Product_Details!$G:$G,"mens") -> Womens | K153: =COUNTIFS($J:$J, J153) / COUNTIFS($J:$J, J153, $E:$E, E153) -> 1883.75
A154: d5e9a6 | B154: 3 | C154: 22 | D154: t | E154: f77cc2 | F154: 0.020461806 | G154: =_xlfn.XLOOKUP($A154,Product_pricing!$B:$B,Product_pricing!$C:$C) -> 23 | H154: =B154*G154*(1-C154/100) -> 53.82 | I154: =(H154/SUM($H:$H))*1000 -> 0.047492823 | J154: =_xlfn.XLOOKUP(A154,Product_Details!$A:$A,Product_Details!$G:$G,"mens") -> Womens | K154: =COUNTIFS($J:$J, J154) / COUNTIFS($J:$J, J154, $E:$E, E154) -> 1883.75
A155: 9ec847 | B155: 3 | C155: 22 | D155: t | E155: f77cc2 | F155: 0.020461806 | G155: =_xlfn.XLOOKUP($A155,Product_pricing!$B:$B,Product_pricing!$C:$C) -> 54 | H155: =B155*G155*(1-C155/100) -> 126.36 | I155: =(H155/SUM($H:$H))*1000 -> 0.11150489 | J155: =_xlfn.XLOOKUP(A155,Product_Details!$A:$A,Product_Details!$G:$G,"mens") -> Womens | K155: =COUNTIFS($J:$J, J155) / COUNTIFS($J:$J, J155, $E:$E, E155) -> 1883.75
A156: 5d267b | B156: 3 | C156: 22 | D156: t | E156: f77cc2 | F156: 0.020461806 | G156: =_xlfn.XLOOKUP($A156,Product_pricing!$B:$B,Product_pricing!$C:$C) -> 40 | H156: =B156*G156*(1-C156/100) -> 93.6 | I156: =(H156/SUM($H:$H))*1000 -> 0.082596214 | J156: =_xlfn.XLOOKUP(A156,Product_Details!$A:$A,Product_Details!$G:$G,"mens") -> Mens | K156: =COUNTIFS($J:$J, J156) / COUNTIFS($J:$J, J156, $E:$E, E156) -> 2520
A157: c8d436 | B157: 5 | C157: 22 | D157: t | E157: f77cc2 | F157: 0.020461806 | G157: =_xlfn.XLOOKUP($A157,Product_pricing!$B:$B,Product_pricing!$C:$C) -> 10 | H157: =B157*G157*(1-C157/100) -> 39 | I157: =(H157/SUM($H:$H))*1000 -> 0.034415089 | J157: =_xlfn.XLOOKUP(A157,Product_Details!$A:$A,Product_Details!$G:$G,"mens") -> Mens | K157: =COUNTIFS($J:$J, J157) / COUNTIFS($J:$J, J157, $E:$E, E157) -> 2520
A158: 2a2353 | B158: 5 | C158: 22 | D158: t | E158: f77cc2 | F158: 0.020461806 | G158: =_xlfn.XLOOKUP($A158,Product_pricing!$B:$B,Product_pricing!$C:$C) -> 57 | H158: =B158*G158*(1-C158/100) -> 222.3 | I158: =(H158/SUM($H:$H))*1000 -> 0.19616601 | J158: =_xlfn.XLOOKUP(A158,Product_Details!$A:$A,Product_Details!$G:$G,"mens") -> Mens | K158: =COUNTIFS($J:$J, J158) / COUNTIFS($J:$J, J158, $E:$E, E158) -> 2520
... A363: 2feb6b | B363: 3 | C363: 21 | D363: f | E363: 3c2972 | F363: 0.030993056 | G363: =_xlfn.XLOOKUP($A363,Product_pricing!$B:$B,Product_pricing!$C:$C) -> 29 | H363: =B363*G363*(1-C363/100) -> 68.73 | I363: =(H363/SUM($H:$H))*1000 -> 0.060649976 | J363: =_xlfn.XLOOKUP(A363,Product_Details!$A:$A,Product_Details!$G:$G,"mens") -> Mens | K363: =COUNTIFS($J:$J, J363) / COUNTIFS($J:$J, J363, $E:$E, E363) -> 1890
A364: e31d39 | B364: 4 | C364: 4 | D364: t | E364: 916293 | F364: 0.02225 | G364: =_xlfn.XLOOKUP($A364,Product_pricing!$B:$B,Product_pricing!$C:$C) -> 10 | H364: =B364*G364*(1-C364/100) -> 38.4 | I364: =(H364/SUM($H:$H))*1000 -> 0.033885626 | J364: =_xlfn.XLOOKUP(A364,Product_Details!$A:$A,Product_Details!$G:$G,"mens") -> Womens | K364: =COUNTIFS($J:$J, J364) / COUNTIFS($J:$J, J364, $E:$E, E364) -> 3767.5
A365: d5e9a6 | B365: 3 | C365: 4 | D365: t | E365: 916293 | F365: 0.02225 | G365: =_xlfn.XLOOKUP($A365,Product_pricing!$B:$B,Product_pricing!$C:$C) -> 23 | H365: =B365*G365*(1-C365/100) -> 66.24 | I365: =(H365/SUM($H:$H))*1000 -> 0.058452705 | J365: =_xlfn.XLOOKUP(A365,Product_Details!$A:$A,Product_Details!$G:$G,"mens") -> Womens | K365: =COUNTIFS($J:$J, J365) / COUNTIFS($J:$J, J365, $E:$E, E365) -> 3767.5
A366: b9a74d | B366: 4 | C366: 4 | D366: t | E366: 916293 | F366: 0.02225 | G366: =_xlfn.XLOOKUP($A366,Product_pricing!$B:$B,Product_pricing!$C:$C) -> 17 | H366: =B366*G366*(1-C366/100) -> 65.28 | I366: =(H366/SUM($H:$H))*1000 -> 0.057605564 | J366: =_xlfn.XLOOKUP(A366,Product_Details!$A:$A,Product_Details!$G:$G,"mens") -> Mens | K366: =COUNTIFS($J:$J, J366) / COUNTIFS($J:$J, J366, $E:$E, E366) -> 3780
A367: 2feb6b | B367: 4 | C367: 4 | D367: t | E367: 916293 | F367: 0.02225 | G367: =_xlfn.XLOOKUP($A367,Product_pricing!$B:$B,Product_pricing!$C:$C) -> 29 | H367: =B367*G367*(1-C367/100) -> 111.36 | I367: =(H367/SUM($H:$H))*1000 -> 0.098268316 | J367: =_xlfn.XLOOKUP(A367,Product_Details!$A:$A,Product_Details!$G:$G,"mens") -> Mens | K367: =COUNTIFS($J:$J, J367) / COUNTIFS($J:$J, J367, $E:$E, E367) -> 3780
A368: e83aa3 | B368: 2 | C368: 18 | D368: t | E368: 144b5e | F368: 0.01278125 | G368: =_xlfn.XLOOKUP($A368,Product_pricing!$B:$B,Product_pricing!$C:$C) -> 32 | H368: =B368*G368*(1-C368/100) -> 52.48 | I368: =(H368/SUM($H:$H))*1000 -> 0.046310356 | J368: =_xlfn.XLOOKUP(A368,Product_Details!$A:$A,Product_Details!$G:$G,"mens") -> Womens | K368: =COUNTIFS($J:$J, J368) / COUNTIFS($J:$J, J368, $E:$E, E368) -> 2511.6667
A369: e31d39 | B369: 2 | C369: 18 | D369: t | E369: 144b5e | F369: 0.01278125 | G369: =_xlfn.XLOOKUP($A369,Product_pricing!$B:$B,Product_pricing!$C:$C) -> 10 | H369: =B369*G369*(1-C369/100) -> 16.4 | I369: =(H369/SUM($H:$H))*1000 -> 0.014471986 | J369: =_xlfn.XLOOKUP(A369,Product_Details!$A:$A,Product_Details!$G:$G,"mens") -> Womens | K369: =COUNTIFS($J:$J, J369) / COUNTIFS($J:$J, J369, $E:$E, E369) -> 2511.6667
A370: 72f5d4 | B370: 1 | C370: 18 | D370: t | E370: 144b5e | F370: 0.01278125 | G370: =_xlfn.XLOOKUP($A370,Product_pricing!$B:$B,Product_pricing!$C:$C) -> 19 | H370: =B370*G370*(1-C370/100) -> 15.58 | I370: =(H370/SUM($H:$H))*1000 -> 0.013748387 | J370: =_xlfn.XLOOKUP(A370,Product_Details!$A:$A,Product_Details!$G:$G,"mens") -> Womens | K370: =COUNTIFS($J:$J, J370) / COUNTIFS($J:$J, J370, $E:$E, E370) -> 2511.6667
A371: 5d267b | B371: 5 | C371: 18 | D371: t | E371: 144b5e | F371: 0.01278125 | G371: =_xlfn.XLOOKUP($A371,Product_pricing!$B:$B,Product_pricing!$C:$C) -> 40 | H371: =B371*G371*(1-C371/100) -> 164 | I371: =(H371/SUM($H:$H))*1000 -> 0.14471986 | J371: =_xlfn.XLOOKUP(A371,Product_Details!$A:$A,Product_Details!$G:$G,"mens") -> Mens | K371: =COUNTIFS($J:$J, J371) / COUNTIFS($J:$J, J371, $E:$E, E371) -> 3780
A372: f084eb | B372: 1 | C372: 18 | D372: t | E372: 144b5e | F372: 0.01278125 | G372: =_xlfn.XLOOKUP($A372,Product_pricing!$B:$B,Product_pricing!$C:$C) -> 36 | H372: =B372*G372*(1-C372/100) -> 29.52 | I372: =(H372/SUM($H:$H))*1000 -> 0.026049575 | J372: =_xlfn.XLOOKUP(A372,Product_Details!$A:$A,Product_Details!$G:$G,"mens") -> Mens | K372: =COUNTIFS($J:$J, J372) / COUNTIFS($J:$J, J372, $E:$E, E372) -> 3780
A373: c4a632 | B373: 4 | C373: 0 | D373: f | E373: f4dfc4 | F373: 0.0015949074 | G373: =_xlfn.XLOOKUP($A373,Product_pricing!$B:$B,Product_pricing!$C:$C) -> 13 | H373: =B373*G373*(1-C373/100) -> 52 | I373: =(H373/SUM($H:$H))*1000 -> 0.045886785 | J373: =_xlfn.XLOOKUP(A373,Product_Details!$A:$A,Product_Details!$G:$G,"mens") -> Womens | K373: =COUNTIFS($J:$J, J373) / COUNTIFS($J:$J, J373, $E:$E, E373) -> 3767.5
A374: 72f5d4 | B374: 4 | C374: 0 | D374: f | E374: f4dfc4 | F374: 0.0015949074 | G374: =_xlfn.XLOOKUP($A374,Product_pricing!$B:$B,Product_pricing!$C:$C) -> 19 | H374: =B374*G374*(1-C374/100) -> 76 | I374: =(H374/SUM($H:$H))*1000 -> 0.067065302 | J374: =_xlfn.XLOOKUP(A374,Product_Details!$A:$A,Product_Details!$G:$G,"mens") -> Womens | K374: =COUNTIFS($J:$J, J374) / COUNTIFS($J:$J, J374, $E:$E, E374) -> 3767.5
A375: 5d267b | B375: 3 | C375: 0 | D375: f | E375: f4dfc4 | F375: 0.0015949074 | G375: =_xlfn.XLOOKUP($A375,Product_pricing!$B:$B,Product_pricing!$C:$C) -> 40 | H375: =B375*G375*(1-C375/100) -> 120 | I375: =(H375/SUM($H:$H))*1000 -> 0.10589258 | J375: =_xlfn.XLOOKUP(A375,Product_Details!$A:$A,Product_Details!$G:$G,"mens") -> Mens | K375: =COUNTIFS($J:$J, J375) / COUNTIFS($J:$J, J375, $E:$E, E375) -> 3780
A376: 2a2353 | B376: 3 | C376: 0 | D376: f | E376: f4dfc4 | F376: 0.0015949074 | G376: =_xlfn.XLOOKUP($A376,Product_pricing!$B:$B,Product_pricing!$C:$C) -> 57 | H376: =B376*G376*(1-C376/100) -> 171 | I376: =(H376/SUM($H:$H))*1000 -> 0.15089693 | J376: =_xlfn.XLOOKUP(A376,Product_Details!$A:$A,Product_Details!$G:$G,"mens") -> Mens | K376: =COUNTIFS($J:$J, J376) / COUNTIFS($J:$J, J376, $E:$E, E376) -> 3780
A377: c4a632 | B377: 5 | C377: 12 | D377: t | E377: f84e54 | F377: 0.016736111 | G377: =_xlfn.XLOOKUP($A377,Product_pricing!$B:$B,Product_pricing!$C:$C) -> 13 | H377: =B377*G377*(1-C377/100) -> 57.2 | I377: =(H377/SUM($H:$H))*1000 -> 0.050475464 | J377: =_xlfn.XLOOKUP(A377,Product_Details!$A:$A,Product_Details!$G:$G,"mens") -> Womens | K377: =COUNTIFS($J:$J, J377) / COUNTIFS($J:$J, J377, $E:$E, E377) -> 1883.75
A378: e83aa3 | B378: 4 | C378: 12 | D378: t | E378: f84e54 | F378: 0.016736111 | G378: =_xlfn.XLOOKUP($A378,Product_pricing!$B:$B,Product_pricing!$C:$C) -> 32 | H378: =B378*G378*(1-C378/100) -> 112.64 | I378: =(H378/SUM($H:$H))*1000 -> 0.099397837 | J378: =_xlfn.XLOOKUP(A378,Product_Details!$A:$A,Product_Details!$G:$G,"mens") -> Womens | K378: =COUNTIFS($J:$J, J378) / COUNTIFS($J:$J, J378, $E:$E, E378) -> 1883.75
A379: d5e9a6 | B379: 3 | C379: 12 | D379: t | E379: f84e54 | F379: 0.016736111 | G379: =_xlfn.XLOOKUP($A379,Product_pricing!$B:$B,Product_pricing!$C:$C) -> 23 | H379: =B379*G379*(1-C379/100) -> 60.72 | I379: =(H379/SUM($H:$H))*1000 -> 0.053581646 | J379: =_xlfn.XLOOKUP(A379,Product_Details!$A:$A,Product_Details!$G:$G,"mens") -> Womens | K379: =COUNTIFS($J:$J, J379) / COUNTIFS($J:$J, J379, $E:$E, E379) -> 1883.75
... A390: f084eb | B390: 5 | C390: 8 | D390: t | E390: 76dbcb | F390: 0.033791667 | G390: =_xlfn.XLOOKUP($A390,Product_pricing!$B:$B,Product_pricing!$C:$C) -> 36 | H390: =B390*G390*(1-C390/100) -> 165.6 | I390: =(H390/SUM($H:$H))*1000 -> 0.14613176 | J390: =_xlfn.XLOOKUP(A390,Product_Details!$A:$A,Product_Details!$G:$G,"mens") -> Mens | K390: =COUNTIFS($J:$J, J390) / COUNTIFS($J:$J, J390, $E:$E, E390) -> 2520
A391: c4a632 | B391: 5 | C391: 8 | D391: f | E391: 218000000000 | F391: 0.034450231 | G391: =_xlfn.XLOOKUP($A391,Product_pricing!$B:$B,Product_pricing!$C:$C) -> 13 | H391: =B391*G391*(1-C391/100) -> 59.8 | I391: =(H391/SUM($H:$H))*1000 -> 0.052769803 | J391: =_xlfn.XLOOKUP(A391,Product_Details!$A:$A,Product_Details!$G:$G,"mens") -> Womens | K391: =COUNTIFS($J:$J, J391) / COUNTIFS($J:$J, J391, $E:$E, E391) -> 2511.6667
A392: e83aa3 | B392: 1 | C392: 8 | D392: f | E392: 218000000000 | F392: 0.034450231 | G392: =_xlfn.XLOOKUP($A392,Product_pricing!$B:$B,Product_pricing!$C:$C) -> 32 | H392: =B392*G392*(1-C392/100) -> 29.44 | I392: =(H392/SUM($H:$H))*1000 -> 0.02597898 | J392: =_xlfn.XLOOKUP(A392,Product_Details!$A:$A,Product_Details!$G:$G,"mens") -> Womens | K392: =COUNTIFS($J:$J, J392) / COUNTIFS($J:$J, J392, $E:$E, E392) -> 2511.6667
A393: 72f5d4 | B393: 5 | C393: 8 | D393: f | E393: 218000000000 | F393: 0.034450231 | G393: =_xlfn.XLOOKUP($A393,Product_pricing!$B:$B,Product_pricing!$C:$C) -> 19 | H393: =B393*G393*(1-C393/100) -> 87.4 | I393: =(H393/SUM($H:$H))*1000 -> 0.077125097 | J393: =_xlfn.XLOOKUP(A393,Product_Details!$A:$A,Product_Details!$G:$G,"mens") -> Womens | K393: =COUNTIFS($J:$J, J393) / COUNTIFS($J:$J, J393, $E:$E, E393) -> 2511.6667
A394: 5d267b | B394: 3 | C394: 8 | D394: f | E394: 218000000000 | F394: 0.034450231 | G394: =_xlfn.XLOOKUP($A394,Product_pricing!$B:$B,Product_pricing!$C:$C) -> 40 | H394: =B394*G394*(1-C394/100) -> 110.4 | I394: =(H394/SUM($H:$H))*1000 -> 0.097421175 | J394: =_xlfn.XLOOKUP(A394,Product_Details!$A:$A,Product_Details!$G:$G,"mens") -> Mens | K394: =COUNTIFS($J:$J, J394) / COUNTIFS($J:$J, J394, $E:$E, E394) -> 1890
A395: c8d436 | B395: 5 | C395: 8 | D395: f | E395: 218000000000 | F395: 0.034450231 | G395: =_xlfn.XLOOKUP($A395,Product_pricing!$B:$B,Product_pricing!$C:$C) -> 10 | H395: =B395*G395*(1-C395/100) -> 46 | I395: =(H395/SUM($H:$H))*1000 -> 0.040592156 | J395: =_xlfn.XLOOKUP(A395,Product_Details!$A:$A,Product_Details!$G:$G,"mens") -> Mens | K395: =COUNTIFS($J:$J, J395) / COUNTIFS($J:$J, J395, $E:$E, E395) -> 1890
A396: f084eb | B396: 2 | C396: 8 | D396: f | E396: 218000000000 | F396: 0.034450231 | G396: =_xlfn.XLOOKUP($A396,Product_pricing!$B:$B,Product_pricing!$C:$C) -> 36 | H396: =B396*G396*(1-C396/100) -> 66.24 | I396: =(H396/SUM($H:$H))*1000 -> 0.058452705 | J396: =_xlfn.XLOOKUP(A396,Product_Details!$A:$A,Product_Details!$G:$G,"mens") -> Mens | K396: =COUNTIFS($J:$J, J396) / COUNTIFS($J:$J, J396, $E:$E, E396) -> 1890
A397: b9a74d | B397: 5 | C397: 8 | D397: f | E397: 218000000000 | F397: 0.034450231 | G397: =_xlfn.XLOOKUP($A397,Product_pricing!$B:$B,Product_pricing!$C:$C) -> 17 | H397: =B397*G397*(1-C397/100) -> 78.2 | I397: =(H397/SUM($H:$H))*1000 -> 0.069006666 | J397: =_xlfn.XLOOKUP(A397,Product_Details!$A:$A,Product_Details!$G:$G,"mens") -> Mens | K397: =COUNTIFS($J:$J, J397) / COUNTIFS($J:$J, J397, $E:$E, E397) -> 1890
A398: c4a632 | B398: 2 | C398: 14 | D398: f | E398: fe3190 | F398: 0.031094907 | G398: =_xlfn.XLOOKUP($A398,Product_pricing!$B:$B,Product_pricing!$C:$C) -> 13 | H398: =B398*G398*(1-C398/100) -> 22.36 | I398: =(H398/SUM($H:$H))*1000 -> 0.019731318 | J398: =_xlfn.XLOOKUP(A398,Product_Details!$A:$A,Product_Details!$G:$G,"mens") -> Womens | K398: =COUNTIFS($J:$J, J398) / COUNTIFS($J:$J, J398, $E:$E, E398) -> 2511.6667
A399: d5e9a6 | B399: 4 | C399: 14 | D399: f | E399: fe3190 | F399: 0.031094907 | G399: =_xlfn.XLOOKUP($A399,Product_pricing!$B:$B,Product_pricing!$C:$C) -> 23 | H399: =B399*G399*(1-C399/100) -> 79.12 | I399: =(H399/SUM($H:$H))*1000 -> 0.069818509 | J399: =_xlfn.XLOOKUP(A399,Product_Details!$A:$A,Product_Details!$G:$G,"mens") -> Womens | K399: =COUNTIFS($J:$J, J399) / COUNTIFS($J:$J, J399, $E:$E, E399) -> 2511.6667
A400: 72f5d4 | B400: 4 | C400: 14 | D400: f | E400: fe3190 | F400: 0.031094907 | G400: =_xlfn.XLOOKUP($A400,Product_pricing!$B:$B,Product_pricing!$C:$C) -> 19 | H400: =B400*G400*(1-C400/100) -> 65.36 | I400: =(H400/SUM($H:$H))*1000 -> 0.057676159 | J400: =_xlfn.XLOOKUP(A400,Product_Details!$A:$A,Product_Details!$G:$G,"mens") -> Womens | K400: =COUNTIFS($J:$J, J400) / COUNTIFS($J:$J, J400, $E:$E, E400) -> 2511.6667
A401: e83aa3 | B401: 3 | C401: 3 | D401: f | E401: 69cc4a | F401: 0.026324074 | G401: =_xlfn.XLOOKUP($A401,Product_pricing!$B:$B,Product_pricing!$C:$C) -> 32 | H401: =B401*G401*(1-C401/100) -> 93.12 | I401: =(H401/SUM($H:$H))*1000 -> 0.082172643 | J401: =_xlfn.XLOOKUP(A401,Product_Details!$A:$A,Product_Details!$G:$G,"mens") -> Womens | K401: =COUNTIFS($J:$J, J401) / COUNTIFS($J:$J, J401, $E:$E, E401) -> 3767.5
A402: 9ec847 | B402: 5 | C402: 3 | D402: f | E402: 69cc4a | F402: 0.026324074 | G402: =_xlfn.XLOOKUP($A402,Product_pricing!$B:$B,Product_pricing!$C:$C) -> 54 | H402: =B402*G402*(1-C402/100) -> 261.9 | I402: =(H402/SUM($H:$H))*1000 -> 0.23111056 | J402: =_xlfn.XLOOKUP(A402,Product_Details!$A:$A,Product_Details!$G:$G,"mens") -> Womens | K402: =COUNTIFS($J:$J, J402) / COUNTIFS($J:$J, J402, $E:$E, E402) -> 3767.5
A403: 2a2353 | B403: 4 | C403: 3 | D403: f | E403: 69cc4a | F403: 0.026324074 | G403: =_xlfn.XLOOKUP($A403,Product_pricing!$B:$B,Product_pricing!$C:$C) -> 57 | H403: =B403*G403*(1-C403/100) -> 221.16 | I403: =(H403/SUM($H:$H))*1000 -> 0.19516003 | J403: =_xlfn.XLOOKUP(A403,Product_Details!$A:$A,Product_Details!$G:$G,"mens") -> Mens | K403: =COUNTIFS($J:$J, J403) / COUNTIFS($J:$J, J403, $E:$E, E403) -> 3780
A404: b9a74d | B404: 2 | C404: 3 | D404: f | E404: 69cc4a | F404: 0.026324074 | G404: =_xlfn.XLOOKUP($A404,Product_pricing!$B:$B,Product_pricing!$C:$C) -> 17 | H404: =B404*G404*(1-C404/100) -> 32.98 | I404: =(H404/SUM($H:$H))*1000 -> 0.029102811 | J404: =_xlfn.XLOOKUP(A404,Product_Details!$A:$A,Product_Details!$G:$G,"mens") -> Mens | K404: =COUNTIFS($J:$J, J404) / COUNTIFS($J:$J, J404, $E:$E, E404) -> 3780
A405: e31d39 | B405: 2 | C405: 3 | D405: f | E405: b4fca1 | F405: 0.022150463 | G405: =_xlfn.XLOOKUP($A405,Product_pricing!$B:$B,Product_pricing!$C:$C) -> 10 | H405: =B405*G405*(1-C405/100) -> 19.4 | I405: =(H405/SUM($H:$H))*1000 -> 0.017119301 | J405: =_xlfn.XLOOKUP(A405,Product_Details!$A:$A,Product_Details!$G:$G,"mens") -> Womens | K405: =COUNTIFS($J:$J, J405) / COUNTIFS($J:$J, J405, $E:$E, E405) -> 2511.6667
A406: 72f5d4 | B406: 2 | C406: 3 | D406: f | E406: b4fca1 | F406: 0.022150463 | G406: =_xlfn.XLOOKUP($A406,Product_pricing!$B:$B,Product_pricing!$C:$C) -> 19 | H406: =B406*G406*(1-C406/100) -> 36.86 | I406: =(H406/SUM($H:$H))*1000 -> 0.032526671 | J406: =_xlfn.XLOOKUP(A406,Product_Details!$A:$A,Product_Details!$G:$G,"mens") -> Womens | K406: =COUNTIFS($J:$J, J406) / COUNTIFS($J:$J, J406, $E:$E, E406) -> 2511.6667
A407: 9ec847 | B407: 3 | C407: 3 | D407: f | E407: b4fca1 | F407: 0.022150463 | G407: =_xlfn.XLOOKUP($A407,Product_pricing!$B:$B,Product_pricing!$C:$C) -> 54 | H407: =B407*G407*(1-C407/100) -> 157.14 | I407: =(H407/SUM($H:$H))*1000 -> 0.13866634 | J407: =_xlfn.XLOOKUP(A407,Product_Details!$A:$A,Product_Details!$G:$G,"mens") -> Womens | K407: =COUNTIFS($J:$J, J407) / COUNTIFS($J:$J, J407, $E:$E, E407) -> 2511.6667
A408: 5d267b | B408: 5 | C408: 3 | D408: f | E408: b4fca1 | F408: 0.022150463 | G408: =_xlfn.XLOOKUP($A408,Product_pricing!$B:$B,Product_pricing!$C:$C) -> 40 | H408: =B408*G408*(1-C408/100) -> 194 | I408: =(H408/SUM($H:$H))*1000 -> 0.17119301 | J408: =_xlfn.XLOOKUP(A408,Product_Details!$A:$A,Product_Details!$G:$G,"mens") -> Mens | K408: =COUNTIFS($J:$J, J408) / COUNTIFS($J:$J, J408, $E:$E, E408) -> 3780
A409: 2feb6b | B409: 2 | C409: 3 | D409: f | E409: b4fca1 | F409: 0.022150463 | G409: =_xlfn.XLOOKUP($A409,Product_pricing!$B:$B,Product_pricing!$C:$C) -> 29 | H409: =B409*G409*(1-C409/100) -> 56.26 | I409: =(H409/SUM($H:$H))*1000 -> 0.049645972 | J409: =_xlfn.XLOOKUP(A409,Product_Details!$A:$A,Product_Details!$G:$G,"mens") -> Mens | K409: =COUNTIFS($J:$J, J409) / COUNTIFS($J:$J, J409, $E:$E, E409) -> 3780
... A598: b9a74d | B598: 1 | C598: 24 | D598: t | E598: 0ff5bb | F598: 0.0029236111 | G598: =_xlfn.XLOOKUP($A598,Product_pricing!$B:$B,Product_pricing!$C:$C) -> 17 | H598: =B598*G598*(1-C598/100) -> 12.92 | I598: =(H598/SUM($H:$H))*1000 -> 0.011401101 | J598: =_xlfn.XLOOKUP(A598,Product_Details!$A:$A,Product_Details!$G:$G,"mens") -> Mens | K598: =COUNTIFS($J:$J, J598) / COUNTIFS($J:$J, J598, $E:$E, E598) -> 1890
A599: e83aa3 | B599: 4 | C599: 0 | D599: t | E599: 205200 | F599: 0.0074618056 | G599: =_xlfn.XLOOKUP($A599,Product_pricing!$B:$B,Product_pricing!$C:$C) -> 32 | H599: =B599*G599*(1-C599/100) -> 128 | I599: =(H599/SUM($H:$H))*1000 -> 0.11295209 | J599: =_xlfn.XLOOKUP(A599,Product_Details!$A:$A,Product_Details!$G:$G,"mens") -> Womens | K599: =COUNTIFS($J:$J, J599) / COUNTIFS($J:$J, J599, $E:$E, E599) -> 2511.6667
A600: d5e9a6 | B600: 1 | C600: 0 | D600: t | E600: 205200 | F600: 0.0074618056 | G600: =_xlfn.XLOOKUP($A600,Product_pricing!$B:$B,Product_pricing!$C:$C) -> 23 | H600: =B600*G600*(1-C600/100) -> 23 | I600: =(H600/SUM($H:$H))*1000 -> 0.020296078 | J600: =_xlfn.XLOOKUP(A600,Product_Details!$A:$A,Product_Details!$G:$G,"mens") -> Womens | K600: =COUNTIFS($J:$J, J600) / COUNTIFS($J:$J, J600, $E:$E, E600) -> 2511.6667
A601: 72f5d4 | B601: 4 | C601: 0 | D601: t | E601: 205200 | F601: 0.0074618056 | G601: =_xlfn.XLOOKUP($A601,Product_pricing!$B:$B,Product_pricing!$C:$C) -> 19 | H601: =B601*G601*(1-C601/100) -> 76 | I601: =(H601/SUM($H:$H))*1000 -> 0.067065302 | J601: =_xlfn.XLOOKUP(A601,Product_Details!$A:$A,Product_Details!$G:$G,"mens") -> Womens | K601: =COUNTIFS($J:$J, J601) / COUNTIFS($J:$J, J601, $E:$E, E601) -> 2511.6667
A602: c8d436 | B602: 1 | C602: 0 | D602: t | E602: 205200 | F602: 0.0074618056 | G602: =_xlfn.XLOOKUP($A602,Product_pricing!$B:$B,Product_pricing!$C:$C) -> 10 | H602: =B602*G602*(1-C602/100) -> 10 | I602: =(H602/SUM($H:$H))*1000 -> 0.0088243818 | J602: =_xlfn.XLOOKUP(A602,Product_Details!$A:$A,Product_Details!$G:$G,"mens") -> Mens | K602: =COUNTIFS($J:$J, J602) / COUNTIFS($J:$J, J602, $E:$E, E602) -> 1890
A603: f084eb | B603: 4 | C603: 0 | D603: t | E603: 205200 | F603: 0.0074618056 | G603: =_xlfn.XLOOKUP($A603,Product_pricing!$B:$B,Product_pricing!$C:$C) -> 36 | H603: =B603*G603*(1-C603/100) -> 144 | I603: =(H603/SUM($H:$H))*1000 -> 0.1270711 | J603: =_xlfn.XLOOKUP(A603,Product_Details!$A:$A,Product_Details!$G:$G,"mens") -> Mens | K603: =COUNTIFS($J:$J, J603) / COUNTIFS($J:$J, J603, $E:$E, E603) -> 1890
A604: b9a74d | B604: 1 | C604: 0 | D604: t | E604: 205200 | F604: 0.0074618056 | G604: =_xlfn.XLOOKUP($A604,Product_pricing!$B:$B,Product_pricing!$C:$C) -> 17 | H604: =B604*G604*(1-C604/100) -> 17 | I604: =(H604/SUM($H:$H))*1000 -> 0.015001449 | J604: =_xlfn.XLOOKUP(A604,Product_Details!$A:$A,Product_Details!$G:$G,"mens") -> Mens | K604: =COUNTIFS($J:$J, J604) / COUNTIFS($J:$J, J604, $E:$E, E604) -> 1890
A605: 2feb6b | B605: 1 | C605: 0 | D605: t | E605: 205200 | F605: 0.0074618056 | G605: =_xlfn.XLOOKUP($A605,Product_pricing!$B:$B,Product_pricing!$C:$C) -> 29 | H605: =B605*G605*(1-C605/100) -> 29 | I605: =(H605/SUM($H:$H))*1000 -> 0.025590707 | J605: =_xlfn.XLOOKUP(A605,Product_Details!$A:$A,Product_Details!$G:$G,"mens") -> Mens | K605: =COUNTIFS($J:$J, J605) / COUNTIFS($J:$J, J605, $E:$E, E605) -> 1890
A606: c4a632 | B606: 2 | C606: 9 | D606: f | E606: 42c729 | F606: 0.017646991 | G606: =_xlfn.XLOOKUP($A606,Product_pricing!$B:$B,Product_pricing!$C:$C) -> 13 | H606: =B606*G606*(1-C606/100) -> 23.66 | I606: =(H606/SUM($H:$H))*1000 -> 0.020878487 | J606: =_xlfn.XLOOKUP(A606,Product_Details!$A:$A,Product_Details!$G:$G,"mens") -> Womens | K606: =COUNTIFS($J:$J, J606) / COUNTIFS($J:$J, J606, $E:$E, E606) -> 3767.5
A607: e83aa3 | B607: 2 | C607: 9 | D607: f | E607: 42c729 | F607: 0.017646991 | G607: =_xlfn.XLOOKUP($A607,Product_pricing!$B:$B,Product_pricing!$C:$C) -> 32 | H607: =B607*G607*(1-C607/100) -> 58.24 | I607: =(H607/SUM($H:$H))*1000 -> 0.0513932 | J607: =_xlfn.XLOOKUP(A607,Product_Details!$A:$A,Product_Details!$G:$G,"mens") -> Womens | K607: =COUNTIFS($J:$J, J607) / COUNTIFS($J:$J, J607, $E:$E, E607) -> 3767.5
A608: f084eb | B608: 4 | C608: 9 | D608: f | E608: 42c729 | F608: 0.017646991 | G608: =_xlfn.XLOOKUP($A608,Product_pricing!$B:$B,Product_pricing!$C:$C) -> 36 | H608: =B608*G608*(1-C608/100) -> 131.04 | I608: =(H608/SUM($H:$H))*1000 -> 0.1156347 | J608: =_xlfn.XLOOKUP(A608,Product_Details!$A:$A,Product_Details!$G:$G,"mens") -> Mens | K608: =COUNTIFS($J:$J, J608) / COUNTIFS($J:$J, J608, $E:$E, E608) -> 3780
A609: b9a74d | B609: 2 | C609: 9 | D609: f | E609: 42c729 | F609: 0.017646991 | G609: =_xlfn.XLOOKUP($A609,Product_pricing!$B:$B,Product_pricing!$C:$C) -> 17 | H609: =B609*G609*(1-C609/100) -> 30.94 | I609: =(H609/SUM($H:$H))*1000 -> 0.027302637 | J609: =_xlfn.XLOOKUP(A609,Product_Details!$A:$A,Product_Details!$G:$G,"mens") -> Mens | K609: =COUNTIFS($J:$J, J609) / COUNTIFS($J:$J, J609, $E:$E, E609) -> 3780
A610: e83aa3 | B610: 5 | C610: 1 | D610: f | E610: 1364ee | F610: 0.0064305556 | G610: =_xlfn.XLOOKUP($A610,Product_pricing!$B:$B,Product_pricing!$C:$C) -> 32 | H610: =B610*G610*(1-C610/100) -> 158.4 | I610: =(H610/SUM($H:$H))*1000 -> 0.13977821 | J610: =_xlfn.XLOOKUP(A610,Product_Details!$A:$A,Product_Details!$G:$G,"mens") -> Womens | K610: =COUNTIFS($J:$J, J610) / COUNTIFS($J:$J, J610, $E:$E, E610) -> 2511.6667
A611: e31d39 | B611: 5 | C611: 1 | D611: f | E611: 1364ee | F611: 0.0064305556 | G611: =_xlfn.XLOOKUP($A611,Product_pricing!$B:$B,Product_pricing!$C:$C) -> 10 | H611: =B611*G611*(1-C611/100) -> 49.5 | I611: =(H611/SUM($H:$H))*1000 -> 0.04368069 | J611: =_xlfn.XLOOKUP(A611,Product_Details!$A:$A,Product_Details!$G:$G,"mens") -> Womens | K611: =COUNTIFS($J:$J, J611) / COUNTIFS($J:$J, J611, $E:$E, E611) -> 2511.6667
A612: 72f5d4 | B612: 1 | C612: 1 | D612: f | E612: 1364ee | F612: 0.0064305556 | G612: =_xlfn.XLOOKUP($A612,Product_pricing!$B:$B,Product_pricing!$C:$C) -> 19 | H612: =B612*G612*(1-C612/100) -> 18.81 | I612: =(H612/SUM($H:$H))*1000 -> 0.016598662 | J612: =_xlfn.XLOOKUP(A612,Product_Details!$A:$A,Product_Details!$G:$G,"mens") -> Womens | K612: =COUNTIFS($J:$J, J612) / COUNTIFS($J:$J, J612, $E:$E, E612) -> 2511.6667
...

Sheet Product_pricing
A1: id | B1: product_id | C1: price | D1: Total Qty | E1: product_name
A2: 7 | B2: c4a632 | C2: 13 | D2: =SUMIF(Product_Sales!$A:$A,$B2,Product_Sales!$B:$B) -> 3856 | E2: =_xlfn.XLOOKUP($B2, Product_Details!$A:$A, Product_Details!$C:$C) -> Navy Oversized Jeans - Womens
A3: 8 | B3: e83aa3 | C3: 32 | D3: =SUMIF(Product_Sales!$A:$A,$B3,Product_Sales!$B:$B) -> 3786 | E3: =_xlfn.XLOOKUP($B3, Product_Details!$A:$A, Product_Details!$C:$C) -> Black Straight Jeans - Womens
A4: 9 | B4: e31d39 | C4: 10 | D4: =SUMIF(Product_Sales!$A:$A,$B4,Product_Sales!$B:$B) -> 3707 | E4: =_xlfn.XLOOKUP($B4, Product_Details!$A:$A, Product_Details!$C:$C) -> Cream Relaxed Jeans - Womens
A5: 10 | B5: d5e9a6 | C5: 23 | D5: =SUMIF(Product_Sales!$A:$A,$B5,Product_Sales!$B:$B) -> 3752 | E5: =_xlfn.XLOOKUP($B5, Product_Details!$A:$A, Product_Details!$C:$C) -> Khaki Suit Jacket - Womens
A6: 11 | B6: 72f5d4 | C6: 19 | D6: =SUMIF(Product_Sales!$A:$A,$B6,Product_Sales!$B:$B) -> 3757 | E6: =_xlfn.XLOOKUP($B6, Product_Details!$A:$A, Product_Details!$C:$C) -> Indigo Rain Jacket - Womens
A7: 12 | B7: 9ec847 | C7: 54 | D7: =SUMIF(Product_Sales!$A:$A,$B7,Product_Sales!$B:$B) -> 3876 | E7: =_xlfn.XLOOKUP($B7, Product_Details!$A:$A, Product_Details!$C:$C) -> Grey Fashion Jacket - Womens
A8: 13 | B8: 5d267b | C8: 40 | D8: =SUMIF(Product_Sales!$A:$A,$B8,Product_Sales!$B:$B) -> 3800 | E8: =_xlfn.XLOOKUP($B8, Product_Details!$A:$A, Product_Details!$C:$C) -> White Tee Shirt - Mens
A9: 14 | B9: c8d436 | C9: 10 | D9: =SUMIF(Product_Sales!$A:$A,$B9,Product_Sales!$B:$B) -> 3646 | E9: =_xlfn.XLOOKUP($B9, Product_Details!$A:$A, Product_Details!$C:$C) -> Teal Button Up Shirt - Mens
A10: 15 | B10: 2a2353 | C10: 57 | D10: =SUMIF(Product_Sales!$A:$A,$B10,Product_Sales!$B:$B) -> 3819 | E10: =_xlfn.XLOOKUP($B10, Product_Details!$A:$A, Product_Details!$C:$C) -> Blue Polo Shirt - Mens
A11: 16 | B11: f084eb | C11: 36 | D11: =SUMIF(Product_Sales!$A:$A,$B11,Product_Sales!$B:$B) -> 3792 | E11: =_xlfn.XLOOKUP($B11, Product_Details!$A:$A, Product_Details!$C:$C) -> Navy Solid Socks - Mens
A12: 17 | B12: b9a74d | C12: 17 | D12: =SUMIF(Product_Sales!$A:$A,$B12,Product_Sales!$B:$B) -> 3655 | E12: =_xlfn.XLOOKUP($B12, Product_Details!$A:$A, Product_Details!$C:$C) -> White Striped Socks - Mens
A13: 18 | B13: 2feb6b | C13: 29 | D13: =SUMIF(Product_Sales!$A:$A,$B13,Product_Sales!$B:$B) -> 3770 | E13: =_xlfn.XLOOKUP($B13, Product_Details!$A:$A, Product_Details!$C:$C) -> Pink Fluro Polkadot Socks - Mens

Sheet Product_Details
A1: product_id | B1: price | C1: product_name | D1: category_id | E1: segment_id | F1: style_id | G1: category_name | H1: segment_name | I1: style_name
A2: c4a632 | B2: 13 | C2: Navy Oversized Jeans - Womens | D2: 1 | E2: 3 | F2: 7 | G2: Womens | H2: Jeans | I2: Navy Oversized
A3: e83aa3 | B3: 32 | C3: Black Straight Jeans - Womens | D3: 1 | E3: 3 | F3: 8 | G3: Womens | H3: Jeans | I3: Black Straight
A4: e31d39 | B4: 10 | C4: Cream Relaxed Jeans - Womens | D4: 1 | E4: 3 | F4: 9 | G4: Womens | H4: Jeans | I4: Cream Relaxed
A5: d5e9a6 | B5: 23 | C5: Khaki Suit Jacket - Womens | D5: 1 | E5: 4 | F5: 10 | G5: Womens | H5: Jacket | I5: Khaki Suit
A6: 72f5d4 | B6: 19 | C6: Indigo Rain Jacket - Womens | D6: 1 | E6: 4 | F6: 11 | G6: Womens | H6: Jacket | I6: Indigo Rain
A7: 9ec847 | B7: 54 | C7: Grey Fashion Jacket - Womens | D7: 1 | E7: 4 | F7: 12 | G7: Womens | H7: Jacket | I7: Grey Fashion
A8: 5d267b | B8: 40 | C8: White Tee Shirt - Mens | D8: 2 | E8: 5 | F8: 13 | G8: Mens | H8: Shirt | I8: White Tee
A9: c8d436 | B9: 10 | C9: Teal Button Up Shirt - Mens | D9: 2 | E9: 5 | F9: 14 | G9: Mens | H9: Shirt | I9: Teal Button Up
A10: 2a2353 | B10: 57 | C10: Blue Polo Shirt - Mens | D10: 2 | E10: 5 | F10: 15 | G10: Mens | H10: Shirt | I10: Blue Polo
A11: f084eb | B11: 36 | C11: Navy Solid Socks - Mens | D11: 2 | E11: 6 | F11: 16 | G11: Mens | H11: Socks | I11: Navy Solid
A12: b9a74d | B12: 17 | C12: White Striped Socks - Mens | D12: 2 | E12: 6 | F12: 17 | G12: Mens | H12: Socks | I12: White Striped
A13: 2feb6b | B13: 29 | C13: Pink Fluro Polkadot Socks - Mens | D13: 2 | E13: 6 | F13: 18 | G13: Mens | H13: Socks | I13: Pink Fluro Polkadot

Sheet Product_Hierarchy
A1: id | B1: parent_id | C1: level_text | D1: level_name
A2: 1 | B2: NULL | C2: Womens | D2: Category
A3: 2 | B3: NULL | C3: Mens | D3: Category
A4: 3 | B4: 1 | C4: Jeans | D4: Segment
A5: 4 | B5: 1 | C5: Jacket | D5: Segment
A6: 5 | B6: 2 | C6: Shirt | D6: Segment
A7: 6 | B7: 2 | C7: Socks | D7: Segment
A8: 7 | B8: 3 | C8: Navy Oversized | D8: Style
A9: 8 | B9: 3 | C9: Black Straight | D9: Style
A10: 9 | B10: 3 | C10: Cream Relaxed | D10: Style
A11: 10 | B11: 4 | C11: Khaki Suit | D11: Style
A12: 11 | B12: 4 | C12: Indigo Rain | D12: Style
A13: 12 | B13: 4 | C13: Grey Fashion | D13: Style
A14: 13 | B14: 5 | C14: White Tee | D14: Style
A15: 14 | B15: 5 | C15: Teal Button Up | D15: Style
... A19: 18 | B19: 6 | C19: Pink Fluro Polkadot | D19: Style

Sheet Q3
A1: category | B1: Sum of Total Sales Amount | C1: Average Order Value (AOV)
A2: Mens | B2: 627512.29 | C2: =B2 / SUMIF(Product_Sales!$J:$J, A2, Product_Sales!$K:$K) -> 0.033591368
A3: Womens | B3: 505711.57 | C3: =B3 / SUMIF(Product_Sales!$J:$J, A3, Product_Sales!$K:$K) -> 0.027106222
A4: Grand Total | B4: 1133223.9

Sheet Q4
A1: product_id | B1: product_name | C1: Sum of Total Qty
A2: 2a2353 | B2: Blue Polo Shirt - Mens | C2: 3819
A3: 2feb6b | B3: Pink Fluro Polkadot Socks - Mens | C3: 3770
A4: 5d267b | B4: White Tee Shirt - Mens | C4: 3800
A5: 72f5d4 | B5: Indigo Rain Jacket - Womens | C5: 3757
A6: 9ec847 | B6: Grey Fashion Jacket - Womens | C6: 3876
A7: b9a74d | B7: White Striped Socks - Mens | C7: 3655
A8: c4a632 | B8: Navy Oversized Jeans - Womens | C8: 3856
A9: c8d436 | B9: Teal Button Up Shirt - Mens | C9: 3646
A10: d5e9a6 | B10: Khaki Suit Jacket - Womens | C10: 3752
A11: e31d39 | B11: Cream Relaxed Jeans - Womens | C11: 3707
A12: e83aa3 | B12: Black Straight Jeans - Womens | C12: 3786
A13: f084eb | B13: Navy Solid Socks - Mens | C13: 3792
A14: (blank)
A15: Grand Total | C15: 45216

Sheet Q5
A1: category | B1: Sum of Total Sales Amount
A2: Mens | B2: 627512.29
A3: Womens | B3: 505711.57
A4: Grand Total | B4: 1133223.9
